los_angeles_citywide_data_style/__init__.py
los_angeles_citywide_data_style/_version.py
los_angeles_citywide_data_style/citywide.mplstyle
los_angeles_citywide_data_style/cmap.py
los_angeles_citywide_data_style-0.1.0.dist-info/LICENSE
los_angeles_citywide_data_style-0.1.0.dist-info/METADATA
los_angeles_citywide_data_style-0.1.0.dist-info/WHEEL
los_angeles_citywide_data_style-0.1.0.dist-info/top_level.txt
los_angeles_citywide_data_style-0.1.0.dist-info/RECORD
