Metadata-Version: 2.1
Name: los-angeles-citywide-data-style
Version: 0.1.0
Summary: Style package for City of Los Angeles data science projects
Home-page: https://github.com/CityOfLosAngeles/los-angeles-citywide-data-style
Maintainer: Ian Rose
Maintainer-email: ian.rose@lacity.org
License: Apache-2.0 license
Keywords: matplotlib
Platform: UNKNOWN
Requires-Dist: matplotlib (>=1.5)
